MANIFEST.in
README.rst
setup.py
django_mptt_treechangelist.egg-info/PKG-INFO
django_mptt_treechangelist.egg-info/SOURCES.txt
django_mptt_treechangelist.egg-info/dependency_links.txt
django_mptt_treechangelist.egg-info/requires.txt
django_mptt_treechangelist.egg-info/top_level.txt
mptt_treechangelist/__init__.py
mptt_treechangelist/admin.py
mptt_treechangelist/forms.py
mptt_treechangelist/static/mptt_treechangelist/js/jquery.cookie.js
mptt_treechangelist/static/mptt_treechangelist/js/treechangelist.js
mptt_treechangelist/templates/admin/tree_change_list.html