Metadata-Version: 1.1
Name: django-mptt-treechangelist
Version: 0.1
Summary: MPTT Tree Change List Django
Home-page: https://github.com/blancltd/django-mptt-treechangelist
Author: Alex Tomkins
Author-email: alex@hawkz.com
License: BSD-2
Platform: any
Classifier: Environment :: Web Environment
Classifier: Framework :: Django
Classifier: License :: OSI Approved :: BSD License
Classifier: Operating System :: OS Independent
Classifier: Programming Language :: Python
